{
  "sources": [
    {
      "href": "https://mainichi.jp/rss/etc/mainichi-enta.rss",
      "articles": [
        {
          "description": "竹井千代（杉咲花）が出演するラジオドラマ「お父さんはお人好（よ）し」は、果物屋を営む夫婦と１２人の子どもたちが巻き起こすホームドラマで、千代と漫才師の花車当郎（塚地武雅）が夫婦役。初めての台本読み合わせの日、千代は出演者に互いに役の名前で呼び合わないかと提案する。鶴亀新喜劇やうどん店「岡福」の人た",
          "link": "https://mainichi.jp/articles/20210502/ddm/018/200/027000c",
          "publishedOn": "2021-05-01T17:00:30.000Z",
          "wordCount": 446,
          "sourceHref": "https://mainichi.jp/rss/etc/mainichi-enta.rss",
          "sourceTitle": "毎日新聞 「エンタメ」RSS",
          "title": "今週のＮＨＫ連続テレビ小説:おちょやん"
        },
        {
          "description": "◆ブルー・アース生命の海（ＢＳ―ＴＢＳ＝後１０・０） 　海の豊かさを伝え、それを守るためにできることを考えるドキュメンタリー番組。出演は元宇宙飛行士の毛利衛、さかなクンら。",
          "link": "https://mainichi.jp/articles/20210502/ddm/018/200/028000c",
          "publishedOn": "2021-05-01T17:00:12.000Z",
          "wordCount": 448,
          "sourceHref": "https://mainichi.jp/rss/etc/mainichi-enta.rss",
          "sourceTitle": "毎日新聞 「エンタメ」RSS",
          "title": "視聴室:ブルー・アース生命の海"
        },
        {
          "description": "１９９８年の長野オリンピック、スキージャンプ・ラージヒル団体金メダルの大逆転劇に隠された実話を描いた映画「ヒノマルソウル～舞台裏の英雄たち～」（毎日新聞社など製作委員会）が、近く全国公開される。裏方として競技を支えたテストジャンパーに焦点を当てた感動作だ。物語の当事者であり、長年日本ジャンプ界をけ",
          "link": "https://mainichi.jp/articles/20210501/ddm/010/200/005000c",
          "publishedOn": "2021-05-01T04:37:29.000Z",
          "wordCount": 445,
          "sourceHref": "https://mainichi.jp/rss/etc/mainichi-enta.rss",
          "sourceTitle": "毎日新聞 「エンタメ」RSS",
          "title": "映画「ヒノマルソウル～舞台裏の英雄たち～」　栄光の陰にドラマ　物語モデルの原田雅彦さん・西方仁也さん、公開目前対談"
        },
        {
          "description": "テーマや長さが絶妙で、心の隙間（すきま）に入り込んでくるＢＳテレ東のドラマ。「高嶺のハナさん」は、年下のダメで可愛い弱木くんを心の中でめでるキャリア系ＯＬ高嶺華が主人公。第３回は、バレンタインデーでの告白失敗や、お菓子の食材候補のわさび農家訪問、体育館で開催された部長の送別会など、充実した内容。ス",
          "link": "https://mainichi.jp/articles/20210501/dde/018/070/005000c",
          "publishedOn": "2021-05-01T03:45:47.000Z",
          "wordCount": 446,
          "sourceHref": "https://mainichi.jp/rss/etc/mainichi-enta.rss",
          "sourceTitle": "毎日新聞 「エンタメ」RSS",
          "title": "辛酸なめ子のＴＶセラピー:テーマや長さが絶妙で…"
        },
        {
          "description": "Ｓｔｙｌｅ２０３０　賢者が映す未来　ＢＳ－ＴＢＳ＝２日午前１１時 　最近、あちこちで「ＳＤＧｓ（持続可能な開発目標）」という言葉を目にする機会が増えた。地球の未来のために、各国が２０３０年までに達成すべき目標を定めたもの。この番組では、３０年に向けた考え方や行動のヒントを、各分野の専門家「賢者」とと",
          "link": "https://mainichi.jp/articles/20210501/dde/018/200/004000c",
          "publishedOn": "2021-05-01T03:43:01.000Z",
          "wordCount": 456,
          "sourceHref": "https://mainichi.jp/rss/etc/mainichi-enta.rss",
          "sourceTitle": "毎日新聞 「エンタメ」RSS",
          "title": "ワイド視聴室:Ｓｔｙｌｅ２０３０　賢者が映す未来　柔らかに探るＳＤＧｓの道"
        },
        {
          "description": "テレビ朝日系のニュース情報番組「大下容子ワイド！スクランブル」（月～金曜午前１０時２５分）で司会を務める大下容子アナウンサー（５０）は昨年６月、同社の現役アナとして初めて役員待遇のエグゼクティブアナウンサーに昇格した。女性の役員や管理職比率が低い日本企業だが、情報番組の制作現場も男性が多い。女性の",
          "link": "https://mainichi.jp/articles/20210501/dde/018/200/007000c",
          "publishedOn": "2021-05-01T03:42:00.000Z",
          "wordCount": 442,
          "sourceHref": "https://mainichi.jp/rss/etc/mainichi-enta.rss",
          "sourceTitle": "毎日新聞 「エンタメ」RSS",
          "title": "女性目線、いかに生かすか　テレ朝系「ワイド！スクランブル」司会、大下容子アナ"
        },
        {
          "description": "日曜劇場「ドラゴン桜」（ＴＢＳ系、日曜午後９時）が始まった。「半沢直樹」の７年を超える、１６年ぶりの続編だ。しかも主人公は同じだが、雰囲気は「別物」と言っていいほど異なっている。それは一体なぜなのか。",
          "link": "https://mainichi.jp/articles/20210501/dde/018/070/006000c",
          "publishedOn": "2021-05-01T03:12:41.000Z",
          "wordCount": 451,
          "sourceHref": "https://mainichi.jp/rss/etc/mainichi-enta.rss",
          "sourceTitle": "毎日新聞 「エンタメ」RSS",
          "title": "週刊テレビ評:１６年ぶりの「ドラゴン桜」　原作と「別物」、期待と戸惑い＝碓井広義"
        },
        {
          "description": "ジャニーズ事務所は３０日、所属する歌手で俳優の近藤真彦さん（５６）が同日付で事務所を退所したと発表した。事務所によると、近藤さんから「これからの人生、自分の責任において芸能とレースの道を歩んでいきたい」と申し出があったといい、近藤さんの意向を尊重したという。自動車レースのレーシングチームの監督業と",
          "link": "https://mainichi.jp/articles/20210501/ddm/012/200/139000c",
          "publishedOn": "2021-04-30T17:01:54.000Z",
          "wordCount": 438,
          "sourceHref": "https://mainichi.jp/rss/etc/mainichi-enta.rss",
          "sourceTitle": "毎日新聞 「エンタメ」RSS",
          "title": "近藤真彦さん、ジャニーズ退所"
        },
        {
          "description": "■教育・教養・実用 （１）真相報道バンキシャ！　　　　　　　　　日テレ　１５．６　日 （２）新・情報７ｄａｙｓニュースキャスター　ＴＢＳ　１５．３　土 （３）サンデーモーニング　　　　　　　　　　　同　　１４．６　日",
          "link": "https://mainichi.jp/articles/20210501/ddm/018/200/025000c",
          "publishedOn": "2021-04-30T17:01:32.000Z",
          "wordCount": 464,
          "sourceHref": "https://mainichi.jp/rss/etc/mainichi-enta.rss",
          "sourceTitle": "毎日新聞 「エンタメ」RSS",
          "title": "視聴率:４月１９～２５日"
        },
        {
          "description": "◆コタローは１人暮らし（朝日＝後１１・３０） 　あるアパートに引っ越してきた１人暮らしの５歳児、さとうコタロー（川原瑛都）と住人との交流を描いたハートフルコメディーの第２話。原作は津村マミの同名人気コミック。",
          "link": "https://mainichi.jp/articles/20210501/ddm/018/200/023000c",
          "publishedOn": "2021-04-30T17:01:06.000Z",
          "wordCount": 450,
          "sourceHref": "https://mainichi.jp/rss/etc/mainichi-enta.rss",
          "sourceTitle": "毎日新聞 「エンタメ」RSS",
          "title": "視聴室:コタローは１人暮らし"
        },
        {
          "description": "２月に米人気歌手のレディー・ガガさん（３５）の愛犬３匹を散歩させていた男性が銃撃され、うち２匹が連れ去られた事件で、ロサンゼルス市警は２９日、１８～５０歳の容疑者の男女５人を殺人未遂などの罪で訴追したと発表した。米メディアによると、５人のうち４人はギャングのメンバー。２匹の飼い主がガガさんだとは知",
          "link": "https://mainichi.jp/articles/20210430/dde/007/030/026000c",
          "publishedOn": "2021-04-30T05:36:03.000Z",
          "wordCount": 445,
          "sourceHref": "https://mainichi.jp/rss/etc/mainichi-enta.rss",
          "sourceTitle": "毎日新聞 「エンタメ」RSS",
          "title": "ガガさんの犬強奪、５容疑者訴追　「飼い主、知らなかった」"
        },
        {
          "description": "ギャンブルの強さで生徒の階級が決まる名門・私立百花王学園。最狂の賭け狂い、蛇喰夢子（浜辺美波）の脅威に、生徒会は危機感を募らせていた。そこに、２年前の事件で停学処分を受け学園を追われていた視鬼神真玄（藤井流星）が現れる。視鬼神の毒牙は、早乙女芽亜里（森川葵）を家畜に陥れ、夢子や生徒会長の桃喰綺羅莉",
          "link": "https://mainichi.jp/articles/20210430/dde/018/070/005000c",
          "publishedOn": "2021-04-30T05:22:36.000Z",
          "wordCount": 451,
          "sourceHref": "https://mainichi.jp/rss/etc/mainichi-enta.rss",
          "sourceTitle": "毎日新聞 「エンタメ」RSS",
          "title": "シネマの週末・トピックス:賭ケグルイ　絶体絶命ロシアンルーレット"
        },
        {
          "description": "旬の俳優がそろったのを見ただけで、松居大悟監督への期待度が分かるというもの。青春の忘れ物を回収するオトナコドモ男子の感傷物語を、生き生きと描く。 　結婚式で集まった高校の同窓生、いずれも３０歳間近の６人。披露宴の余興で会場をドン引きさせた後、２次会までポカンと時間が空いた。所在なく歩き回る彼らが、",
          "link": "https://mainichi.jp/articles/20210430/dde/018/070/008000c",
          "publishedOn": "2021-04-30T05:21:48.000Z",
          "wordCount": 452,
          "sourceHref": "https://mainichi.jp/rss/etc/mainichi-enta.rss",
          "sourceTitle": "毎日新聞 「エンタメ」RSS",
          "title": "シネマの週末・時代の目:くれなずめ　さえない青春の忘れ物"
        },
        {
          "description": "技能実習生としてベトナムから来日したフォン（ホアン・フォン）、アン、ニューが劣悪な労働環境に耐えかねて脱走した。ブローカーの手引きで、ある漁村にたどり着いた３人は、母国の家族を思いながら働き始めるが、フォンが体調不良に見舞われる。",
          "link": "https://mainichi.jp/articles/20210430/dde/018/070/007000c",
          "publishedOn": "2021-04-30T05:21:19.000Z",
          "wordCount": 448,
          "sourceHref": "https://mainichi.jp/rss/etc/mainichi-enta.rss",
          "sourceTitle": "毎日新聞 「エンタメ」RSS",
          "title": "シネマの週末・トピックス:海辺の彼女たち"
        },
        {
          "description": "妻だったマドンナを起用した「流されて…」で大コケしたかと思えば、「シャーロック・ホームズ」は大当たりしてシリーズ化。当たり外れの差が大きいガイ・リッチー監督、今作は原点回帰。デビュー作「ロック、ストック＆トゥー・スモーキング・バレルズ」を思わせる、アクの強いクセ者が入り乱れる犯罪物語だ。",
          "link": "https://mainichi.jp/articles/20210430/dde/018/070/009000c",
          "publishedOn": "2021-04-30T05:20:49.000Z",
          "wordCount": 452,
          "sourceHref": "https://mainichi.jp/rss/etc/mainichi-enta.rss",
          "sourceTitle": "毎日新聞 「エンタメ」RSS",
          "title": "シネマの週末・この１本:ジェントルメン　クセある悪党入り乱れ"
        },
        {
          "description": "「名探偵コナン　緋色の弾丸」が２週連続１位となり、２位には前週末公開の人気シリーズ最終章、２部作の１作目「るろうに剣心最終章ＴｈｅＦｉｎａｌ」がつけた。しかし動員は「こんなはずじゃなかった」という結果となった。",
          "link": "https://mainichi.jp/articles/20210430/dde/018/070/004000c",
          "publishedOn": "2021-04-30T03:32:34.000Z",
          "wordCount": 449,
          "sourceHref": "https://mainichi.jp/rss/etc/mainichi-enta.rss",
          "sourceTitle": "毎日新聞 「エンタメ」RSS",
          "title": "シネマの週末・データで読解:「映画復興」再度足踏み"
        },
        {
          "description": "◆新番組・あのときキスしておけば（朝日＝後１１・１５） 　松坂桃李主演のラブコメディーの第１話。桃地のぞむ（松坂）はスーパーの店員。仕事は失敗続きで、特に目標もなく生きていた。ある日、ひょんなことから唯月巴（麻生久美子）と知り合う。実は彼女は、桃地の大好きな漫画「ＳＥＩＫＡの空」の作者・蟹釜ジョー",
          "link": "https://mainichi.jp/articles/20210430/ddm/018/200/013000c",
          "publishedOn": "2021-04-29T17:00:30.000Z",
          "wordCount": 449,
          "sourceHref": "https://mainichi.jp/rss/etc/mainichi-enta.rss",
          "sourceTitle": "毎日新聞 「エンタメ」RSS",
          "title": "視聴室:新番組・あのときキスしておけば"
        },
        {
          "description": "「不要不急の外出はいけません」と言われ続けて美しい５月が過ぎるのか。４月の花見でもそうだったなあ。ＢＳ朝日で５月５日放送の「京都ぶらり歴史探訪　今宵（こよい）はリモート花見！～２０２１年　都の美しき桜～」（午後８時）で、失った季節を取り戻したい。",
          "link": "https://mainichi.jp/articles/20210430/ddm/018/200/015000c",
          "publishedOn": "2021-04-29T17:00:18.000Z",
          "wordCount": 449,
          "sourceHref": "https://mainichi.jp/rss/etc/mainichi-enta.rss",
          "sourceTitle": "毎日新聞 「エンタメ」RSS",
          "title": "ＢＳ未来館:見られなかった京都の桜を"
        },
        {
          "description": "東京都内の寄席４軒と落語協会、落語芸術協会が、緊急事態宣言による都の無観客開催の要請に応じず営業を続けている件で、寄席側は２８日、一転して５月１日から１１日まで休業することを決めた。都は２８日午前、無観客の要請に応じない場合は休業を要請すると寄席側に伝え、寄席側が再協議していた。",
          "link": "https://mainichi.jp/articles/20210429/ddm/012/040/054000c",
          "publishedOn": "2021-04-28T17:03:57.000Z",
          "wordCount": 519,
          "sourceHref": "https://mainichi.jp/rss/etc/mainichi-enta.rss",
          "sourceTitle": "毎日新聞 「エンタメ」RSS",
          "title": "新型コロナ　都内の４寄席、一転休業"
        },
        {
          "description": "＜ＴＢＳ系火曜ドラマ「着飾る恋には理由があって」（火曜午後１０時）寺井陽人役＞ 　ルームシェアしている人たちの“うちキュン”ラブストーリーですが、僕が撮影現場でキュンキュンしているのが、こうじ。夏川結衣さん演じる家主の愛犬で、名前は麴から。女の子です。一緒にいると本当に癒やされます。お芝居がまた良",
          "link": "https://mainichi.jp/articles/20210429/ddm/018/200/009000c",
          "publishedOn": "2021-04-28T17:00:38.000Z",
          "wordCount": 450,
          "sourceHref": "https://mainichi.jp/rss/etc/mainichi-enta.rss",
          "sourceTitle": "毎日新聞 「エンタメ」RSS",
          "title": "赤坂電視台:丸山隆平／３　女性同士の距離感が新鮮"
        }
      ]
    },
    {
      "href": "https://www.smashingmagazine.com/feed/",
      "articles": [
        {
          "description": "Do you need a little inspiration boost? Well, then our new collection of wallpapers is for you. Designed with love by the community for the community, the wallpapers are available with and without a calendar for May 2021.",
          "link": "https://smashingmagazine.com/2021/04/desktop-wallpaper-calendars-may-2021/",
          "publishedOn": "2021-04-30T09:00:00.000Z",
          "wordCount": 2139,
          "sourceHref": "https://www.smashingmagazine.com/feed/",
          "sourceTitle": "Articles on Smashing Magazine — For Web Designers And Developers",
          "title": "May Is In The Air (2021 Wallpapers Edition)"
        },
        {
          "description": "Images have also been a key part of the web. They communicate ideas instantly, but they are also a lot heavier than text to load. This means that it’s essential to get loading and displaying them right, if you want to give your users a fantastic first impression. An excerpt from [Addy's new book](https://www.smashingmagazine.com/2021/04/image-optimization-pre-release/) (also, check a [free PDF preview](http://provide.smashingmagazine.com/eBooks/image-optimization-sample-chapter.pdf)).",
          "link": "https://smashingmagazine.com/2021/04/humble-img-element-core-web-vitals/",
          "publishedOn": "2021-04-29T12:15:00.000Z",
          "wordCount": 5289,
          "sourceHref": "https://www.smashingmagazine.com/feed/",
          "sourceTitle": "Articles on Smashing Magazine — For Web Designers And Developers",
          "title": "The Humble `<img>` Element And Core Web Vitals"
        },
        {
          "description": "The cat is out! For the last year, we’ve been working with Addy Osmani on a new Smashing Book all around image optimization. And now it’s here. Meet “Image Optimization”, our practical modern guide to delivering high-quality images on the web with the best performance.",
          "link": "https://smashingmagazine.com/2021/04/image-optimization-pre-release/",
          "publishedOn": "2021-04-28T13:20:00.000Z",
          "wordCount": 2136,
          "sourceHref": "https://www.smashingmagazine.com/feed/",
          "sourceTitle": "Articles on Smashing Magazine — For Web Designers And Developers",
          "title": "Meet Image Optimization, A New Smashing Book By Addy Osmani"
        },
        {
          "description": "Easing functions can change the look and feel of an animation by affecting the rate, or speed, of an animation. In this article, we’re going to take a deep dive into easing functions and see how we can use them to create those natural and stunning animations.",
          "link": "https://smashingmagazine.com/2021/04/easing-functions-css-animations-transitions/",
          "publishedOn": "2021-04-27T12:00:00.000Z",
          "wordCount": 2623,
          "sourceHref": "https://www.smashingmagazine.com/feed/",
          "sourceTitle": "Articles on Smashing Magazine — For Web Designers And Developers",
          "title": "Understanding Easing Functions For CSS Animations And Transitions"
        },
        {
          "description": "Accessibility experts Kate Kalcevich and Mike Gifford introduce readers to \"layered accessibility testing”, a practice of using a variety of tools and approaches at different stages in the digital product lifecycle to catch accessibility issues early &mdash; when it’s easier and cheaper to fix them.",
          "link": "https://smashingmagazine.com/2021/04/bake-layers-accessibility-testing-process/",
          "publishedOn": "2021-04-26T11:00:00.000Z",
          "wordCount": 3279,
          "sourceHref": "https://www.smashingmagazine.com/feed/",
          "sourceTitle": "Articles on Smashing Magazine — For Web Designers And Developers",
          "title": "How To Bake Layers Of Accessibility Testing Into Your Process"
        },
        {
          "description": "The CSS Working Group Editor’s Draft for [Selectors Level 4](https://drafts.csswg.org/selectors-4/) includes several pseudo-class selectors that already have proposal candidates in most modern browsers. This guide will cover ones that currently have the best support along with examples to demonstrate how you can start using them today!",
          "link": "https://smashingmagazine.com/2021/04/guide-supported-modern-css-pseudo-class-selectors/",
          "publishedOn": "2021-04-23T08:30:00.000Z",
          "wordCount": 2431,
          "sourceHref": "https://www.smashingmagazine.com/feed/",
          "sourceTitle": "Articles on Smashing Magazine — For Web Designers And Developers",
          "title": "A Guide To Newly Supported, Modern CSS Pseudo-Class Selectors"
        },
        {
          "description": "Sometimes it’s the little things in web life that make us look twice. From carousels to documentation to cookie disclaimers, here are some sites taking the mundane and sprinkling in a little magic.",
          "link": "https://smashingmagazine.com/2021/04/web-design-done-well-part1/",
          "publishedOn": "2021-04-22T14:00:00.000Z",
          "wordCount": 1764,
          "sourceHref": "https://www.smashingmagazine.com/feed/",
          "sourceTitle": "Articles on Smashing Magazine — For Web Designers And Developers",
          "title": "Web Design Done Well: The Ordinary Made Extraordinary (Part 1)"
        },
        {
          "description": "Incremental Static Regeneration (ISR) is a new evolution of the Jamstack, allowing you to update static content instantly without needing a full rebuild of your site. The hybrid approach of Next.js allows you to use ISR for e-commerce, marketing pages, blog posts, ad-backed media, and more.",
          "link": "https://smashingmagazine.com/2021/04/incremental-static-regeneration-nextjs/",
          "publishedOn": "2021-04-21T13:55:00.000Z",
          "wordCount": 1929,
          "sourceHref": "https://www.smashingmagazine.com/feed/",
          "sourceTitle": "Articles on Smashing Magazine — For Web Designers And Developers",
          "title": "A Complete Guide To Incremental Static Regeneration (ISR) With Next.js"
        },
        {
          "description": "As designers, we are often burdened by the responsibility of producing and managing website content. It’s not our job to write it, but it’s not the client’s either. We can avert disaster by including content production in the design process.",
          "link": "https://smashingmagazine.com/2021/04/content-fundamental-part-web-design-process/",
          "publishedOn": "2021-04-21T08:30:00.000Z",
          "wordCount": 2998,
          "sourceHref": "https://www.smashingmagazine.com/feed/",
          "sourceTitle": "Articles on Smashing Magazine — For Web Designers And Developers",
          "title": "Why Content Is Such A Fundamental Part Of The Web Design Process"
        },
        {
          "description": "Let’s explore the plugins providing GraphQL servers to WordPress. When should we use WPGraphQL, and when the GraphQL API for WordPress? Is there some advantage of one over the other, or some particular task that is easier to accomplish with one of them? In this article, we will find out.",
          "link": "https://smashingmagazine.com/2021/04/making-graphql-work-in-wordpress/",
          "publishedOn": "2021-04-20T09:00:00.000Z",
          "wordCount": 3482,
          "sourceHref": "https://www.smashingmagazine.com/feed/",
          "sourceTitle": "Articles on Smashing Magazine — For Web Designers And Developers",
          "title": "Making GraphQL Work In WordPress"
        },
        {
          "description": "How are Core Web Vitals measured? How do you know your fixes have had the desired effect and when will you see the results in Google Search Console? Let’s figure it out.",
          "link": "https://smashingmagazine.com/2021/04/complete-guide-measure-core-web-vitals/",
          "publishedOn": "2021-04-19T08:30:00.000Z",
          "wordCount": 7206,
          "sourceHref": "https://www.smashingmagazine.com/feed/",
          "sourceTitle": "Articles on Smashing Magazine — For Web Designers And Developers",
          "title": "An In-Depth Guide To Measuring Core Web Vitals"
        },
        {
          "description": "It’s no secret that the technical interview process leaves something to be desired; it’s often riddled with anxiety and stress. In this article, we’ll take a look at seven of the most common mistakes candidates make in their technical interviews and explore ways you can avoid them.",
          "link": "https://smashingmagazine.com/2021/04/mistakes-technical-interviews/",
          "publishedOn": "2021-04-16T09:00:00.000Z",
          "wordCount": 2912,
          "sourceHref": "https://www.smashingmagazine.com/feed/",
          "sourceTitle": "Articles on Smashing Magazine — For Web Designers And Developers",
          "title": "Seven Mistakes To Avoid In Your Technical Interviews"
        },
        {
          "description": "Selling is key to growing your web design business, but it doesn’t have to be complicated! With clear goals, customer research, and proven closing techniques, anyone can find new clients.",
          "link": "https://smashingmagazine.com/2021/04/web-design-clients-fast-part2/",
          "publishedOn": "2021-04-15T11:00:00.000Z",
          "wordCount": 3522,
          "sourceHref": "https://www.smashingmagazine.com/feed/",
          "sourceTitle": "Articles on Smashing Magazine — For Web Designers And Developers",
          "title": "How To Get Web Design Clients Fast (Part 2)"
        },
        {
          "description": "At Smashing, we’ve been busy over the last few months. We’ve set up new workshops, redesigned our navigation, refined performance and improved accessibility. There are subtle UX changes coming in, and we’d love to share what we’ve been cooking.",
          "link": "https://smashingmagazine.com/2021/04/from-cats-with-love-navigation-guides-workshops/",
          "publishedOn": "2021-04-15T10:30:00.000Z",
          "wordCount": 967,
          "sourceHref": "https://www.smashingmagazine.com/feed/",
          "sourceTitle": "Articles on Smashing Magazine — For Web Designers And Developers",
          "title": "From Cats With Love: New Navigation, Guides And Workshops"
        },
        {
          "description": "In this article, we will explore the causes of overflow issues and how to solve them. We will also explore how modern features in the developer tools (DevTools) can make the process of fixing and debugging easier.",
          "link": "https://smashingmagazine.com/2021/04/css-overflow-issues/",
          "publishedOn": "2021-04-14T11:00:00.000Z",
          "wordCount": 1917,
          "sourceHref": "https://www.smashingmagazine.com/feed/",
          "sourceTitle": "Articles on Smashing Magazine — For Web Designers And Developers",
          "title": "Overflow Issues In CSS"
        },
        {
          "description": "In this article, we’ll be building a video streaming app using Nuxt.js and Node.js. Specifically, we’ll build a server-side Node.js app that will handle fetching and streaming videos, generating thumbnails for your videos, and serving captions and subtitles.",
          "link": "https://smashingmagazine.com/2021/04/building-video-streaming-app-nuxtjs-node-express/",
          "publishedOn": "2021-04-13T14:00:00.000Z",
          "wordCount": 3154,
          "sourceHref": "https://www.smashingmagazine.com/feed/",
          "sourceTitle": "Articles on Smashing Magazine — For Web Designers And Developers",
          "title": "Building A Video Streaming App With Nuxt.js, Node And Express"
        },
        {
          "description": "Recently we’ve covered CSS generators, SVG generators and accessible front-end components. This time we look into HTML email, with tools, templates and guides for designers and developers.",
          "link": "https://smashingmagazine.com/2021/04/complete-guide-html-email-templates-tools/",
          "publishedOn": "2021-04-12T12:30:00.000Z",
          "wordCount": 2965,
          "sourceHref": "https://www.smashingmagazine.com/feed/",
          "sourceTitle": "Articles on Smashing Magazine — For Web Designers And Developers",
          "title": "A Complete Guide To HTML Email"
        },
        {
          "description": "UX practitioners can play an important role in growing the UX maturity of the organizations and product teams they work with. This final article in a three-part series presents two additional tactics: education of staff on UX principles and processes.",
          "link": "https://smashingmagazine.com/2021/04/growing-ux-maturity-in-organizations-part-3/",
          "publishedOn": "2021-04-09T19:30:00.000Z",
          "wordCount": 5988,
          "sourceHref": "https://www.smashingmagazine.com/feed/",
          "sourceTitle": "Articles on Smashing Magazine — For Web Designers And Developers",
          "title": "Growing UX Maturity In Organizations: Education And Training (Part 3)"
        },
        {
          "description": "Have you ever struggled to get the green light on your design proposals? Do you feel like your design process needs to be formalized? Is the COVID19 era becoming a challenge for you when working remotely as a designer? Then keep reading to get to know a methodology to document your design process in this article.",
          "link": "https://smashingmagazine.com/2021/04/better-documentation-team-communication-product-design-docs/",
          "publishedOn": "2021-04-08T11:00:00.000Z",
          "wordCount": 1858,
          "sourceHref": "https://www.smashingmagazine.com/feed/",
          "sourceTitle": "Articles on Smashing Magazine — For Web Designers And Developers",
          "title": "Better Documentation And Team Communication With Product Design Docs"
        },
        {
          "description": "Unreliable tests are a living nightmare for anyone who writes automated tests or pays attention to the results. Flaky tests have even given folks nightmares and sleepless nights. In this article, Ramona Schwering shares her experiences to help you get out of this hell or avoid getting into it.",
          "link": "https://smashingmagazine.com/2021/04/flaky-tests-living-nightmare/",
          "publishedOn": "2021-04-07T11:00:00.000Z",
          "wordCount": 4049,
          "sourceHref": "https://www.smashingmagazine.com/feed/",
          "sourceTitle": "Articles on Smashing Magazine — For Web Designers And Developers",
          "title": "Flaky Tests: Getting Rid Of A Living Nightmare In Testing"
        },
        {
          "description": "With many options comes many decisions, and it is easy to drown in all the many benefits of  headless CMS. How do we approach evaluating these options? Let’s figure it out.",
          "link": "https://smashingmagazine.com/2021/04/evaluating-headless/",
          "publishedOn": "2021-04-06T16:10:00.000Z",
          "wordCount": 4083,
          "sourceHref": "https://www.smashingmagazine.com/feed/",
          "sourceTitle": "Articles on Smashing Magazine — For Web Designers And Developers",
          "title": "Don’t Lose Your Head: Evaluating Headless"
        },
        {
          "description": "A guide to vanilla JavaScript code snippets &mdash; with resources and lightweight libraries to help you solve a problem without a large overhead or third-party dependencies.",
          "link": "https://smashingmagazine.com/2021/04/vanilla-javascript-code-snippets/",
          "publishedOn": "2021-04-05T10:30:00.000Z",
          "wordCount": 2018,
          "sourceHref": "https://www.smashingmagazine.com/feed/",
          "sourceTitle": "Articles on Smashing Magazine — For Web Designers And Developers",
          "title": "Vanilla JavaScript Code Snippets"
        }
      ]
    },
    {
      "href": "https://www.freecodecamp.org/news/rss/",
      "articles": [
        {
          "description": "These days, computers can pretty much do anything. Now if you are a frequent computer user like I am, I'm sure you interact with the keyboard all the time. And in this article, I'm going to show you some helpful keyboard shortcuts that will make your work easier",
          "link": "https://www.freecodecamp.org/news/keyboard-shortcuts-improve-productivity/",
          "publishedOn": "2021-04-30T18:37:37.000Z",
          "wordCount": 1334,
          "sourceHref": "https://www.freecodecamp.org/news/rss/",
          "sourceTitle": "freeCodeCamp.org",
          "title": "Keyboard Shortcuts to Improve Your Coding Productivity"
        },
        {
          "description": "In this article, you'll practice your JavaScript skills while streamlining your household chores by creating your very own home inventory system.  I've often found that it's hard to keep track common household items that I buy frequently such as food, spices, medicine, and the like. It's annoying at best and",
          "link": "https://www.freecodecamp.org/news/nodejs-and-cloud-firestore-tutorial-build-a-home-inventory-system/",
          "publishedOn": "2021-04-30T16:26:24.000Z",
          "wordCount": 1429,
          "sourceHref": "https://www.freecodecamp.org/news/rss/",
          "sourceTitle": "freeCodeCamp.org",
          "title": "Node.js and Cloud Firestore Tutorial – How to Build a Home Inventory System"
        },
        {
          "description": "Docker is an open source project that makes it easy to create containers and container-based apps. Docker's lightweight and portable software containers simplify application development, testing, and deployment. We just released a course on the freeCodeCamp.org YouTube channel that will help you learn the core fundamentals of Docker by",
          "link": "https://www.freecodecamp.org/news/learn-docker-by-building-a-node-express-app/",
          "publishedOn": "2021-04-29T20:05:04.000Z",
          "wordCount": 496,
          "sourceHref": "https://www.freecodecamp.org/news/rss/",
          "sourceTitle": "freeCodeCamp.org",
          "title": "Learn Docker by Building a Node / Express App"
        },
        {
          "description": "In this article, I'll teach you CSS Flexbox basics so you can make your own responsive sites. I'll explain how each of Flexbox's properties work, and I'll give you a cheatsheet that covers everything you can do with Flexbox. Let's Go 🎖️ Table of ContentsFlexbox Architectureflex-directionjustify-contentalign-contentalign-itemsalign-selfflex - grow | shrink | wrap | basisShort",
          "link": "https://www.freecodecamp.org/news/css-flexbox-tutorial-with-cheatsheet/",
          "publishedOn": "2021-04-28T19:33:57.000Z",
          "wordCount": 1289,
          "sourceHref": "https://www.freecodecamp.org/news/rss/",
          "sourceTitle": "freeCodeCamp.org",
          "title": "CSS Flexbox Tutorial with Flexbox Properties Cheat Sheet 🎖️"
        },
        {
          "description": "The MERN stack is a popular way to make a full stack web app. MERN stands for MongoDB, Express, React, and Node.js. We just published a course on the freeCodeCamp.org YouTube channel that will teach you how to use the MERN stack by building a restaurant review web",
          "link": "https://www.freecodecamp.org/news/create-a-mern-stack-app-with-a-serverless-backend/",
          "publishedOn": "2021-04-28T14:05:56.000Z",
          "wordCount": 384,
          "sourceHref": "https://www.freecodecamp.org/news/rss/",
          "sourceTitle": "freeCodeCamp.org",
          "title": "Create a MERN Stack App with a Serverless Backend"
        },
        {
          "description": "JavaScript is an easy-to-learn programming language compared to many of its counterparts. However, a few basic concepts need a bit more attention if you want to understand, debug, and write better code.  In this article, we will learn about two such concepts, Execution ContextHoistingAs a beginner to JavaScript, understanding these",
          "link": "https://www.freecodecamp.org/news/javascript-execution-context-and-hoisting/",
          "publishedOn": "2021-04-27T22:53:14.000Z",
          "wordCount": 2010,
          "sourceHref": "https://www.freecodecamp.org/news/rss/",
          "sourceTitle": "freeCodeCamp.org",
          "title": "JavaScript Execution Context and Hoisting Explained with Code Examples"
        },
        {
          "description": "Hi! Welcome. If you are learning Python, then this article is for you. You will find a thorough description of Python syntax and lots of code examples to guide you during your coding journey.  What we will cover:Variable Definitions in PythonHello, World! Program in PythonData Types and Built-in Data",
          "link": "https://www.freecodecamp.org/news/python-code-examples-sample-script-coding-tutorial-for-beginners/",
          "publishedOn": "2021-04-27T19:55:23.000Z",
          "wordCount": 12960,
          "sourceHref": "https://www.freecodecamp.org/news/rss/",
          "sourceTitle": "freeCodeCamp.org",
          "title": "Python Code Examples – Sample Script Coding Tutorial for Beginners"
        },
        {
          "description": "Hello, everyone! In this article we are going to learn how to add the Realm database to an iOS app.  We'll create a simple ToDo app so you can learn how to perform CRUD (Create, Read, Update, Delete) operations in the Realm database. What is Realm?Realm is an open-source",
          "link": "https://www.freecodecamp.org/news/add-realm-database-to-ios-crud-app-with-with-swift/",
          "publishedOn": "2021-04-27T18:21:00.000Z",
          "wordCount": 1815,
          "sourceHref": "https://www.freecodecamp.org/news/rss/",
          "sourceTitle": "freeCodeCamp.org",
          "title": "How to Add the Realm Database to an iOS CRUD App using Swift"
        },
        {
          "description": "What is Lazy Loading?Lazy loading is the process of loading components, modules, or other assets of a website as they're required.  Since Angular creates a SPA (Single Page Application), all of its components are loaded at once. This means that a lot of unnecessary libraries or modules might be",
          "link": "https://www.freecodecamp.org/news/lazy-loading-in-angular-intro-to-ngmodules/",
          "publishedOn": "2021-04-27T18:17:43.000Z",
          "wordCount": 1178,
          "sourceHref": "https://www.freecodecamp.org/news/rss/",
          "sourceTitle": "freeCodeCamp.org",
          "title": "Lazy Loading in Angular – A Beginner&#x27;s Guide to NgModules"
        },
        {
          "description": "In this article, we will build a React application using class components. Then we'll convert it to functional components using React Hooks in a step-by-step way. By building this app, you will learn: How to make API callsHow to implement load more functionalityHow to debug application issuesHow to use async/",
          "link": "https://www.freecodecamp.org/news/build-a-react-application-with-load-more-functionality-react-hooks/",
          "publishedOn": "2021-04-27T18:12:22.000Z",
          "wordCount": 3778,
          "sourceHref": "https://www.freecodecamp.org/news/rss/",
          "sourceTitle": "freeCodeCamp.org",
          "title": "How to Build a React Application with Load More Functionality using React Hooks"
        }
      ]
    }
  ],
  "cliVersion": "1.2.3"
}